shortiepy/__init__.py
shortiepy/__main__.py
shortiepy/app.py
shortiepy/completions/shortiepy.bash
shortiepy/completions/shortiepy.fish
shortiepy/completions/shortiepy.zsh
shortiepy/static/style.css
shortiepy/templates/base.html
shortiepy/templates/index.html
shortiepy/templates/list.html
shortiepy/templates/message.html
shortiepy-1.0.2.dist-info/licenses/LICENSE
shortiepy-1.0.2.dist-info/METADATA
shortiepy-1.0.2.dist-info/WHEEL
shortiepy-1.0.2.dist-info/entry_points.txt
shortiepy-1.0.2.dist-info/top_level.txt
shortiepy-1.0.2.dist-info/RECORD
