Metadata-Version: 2.4
Name: shortiepy
Version: 1.0.2
Summary: A local-only URL shortener (˶˘ ³˘)♡
Author: ポテト ^. .^₎ฅ
Author-email: "ポテト ^. .^₎ฅ" <nya@cheapnightbot.me>
License: MIT
Project-URL: Homepage, https://github.com/CheapNightbot/shortiepy
Project-URL: Repository, https://github.com/CheapNightbot/shortiepy.git
Project-URL: Issues, https://github.com/CheapNightbot/shortiepy/issues
Keywords: cli,shortie,shortiepy,URL shortener
Classifier: Development Status :: 4 - Beta
Classifier: Environment :: Console
Classifier: Intended Audience :: End Users/Desktop
Classifier: License :: OSI Approved :: MIT License
Classifier: Operating System :: OS Independent
Classifier: Programming Language :: Python
Classifier: Programming Language :: Python :: 3 :: Only
Classifier: Topic :: Utilities
Requires-Python: >=3.10
License-File: LICENSE
Requires-Dist: click>=8.3.1
Requires-Dist: colorama>=0.4.6
Requires-Dist: Flask>=3.1.2
Requires-Dist: pyperclip>=1.11.0
Requires-Dist: tabulate>=0.9.0
Requires-Dist: waitress>=3.0.2
Dynamic: license-file
